Metadata-Version: 2.1
Name: Cpuppy
Version: 1.1
Summary: Library for simple CPU simulating
Home-page: UNKNOWN
Author: Katemi
Author-email: thewords32@gmail.com
License: UNKNOWN
Keywords: Binary
Platform: UNKNOWN
Classifier: Development Status :: 5 - Production/Stable
Classifier: Intended Audience :: Education
Classifier: Operating System :: Microsoft :: Windows :: Windows 10
Classifier: License :: OSI Approved :: MIT License
Classifier: Programming Language :: Python :: 3
License-File: LICENSE.txt
